z_gitlab_runner/__about__.py
z_gitlab_runner/__init__.py
z_gitlab_runner-0.0.4.dist-info/METADATA
z_gitlab_runner-0.0.4.dist-info/WHEEL
z_gitlab_runner-0.0.4.dist-info/licenses/LICENSE.txt
z_gitlab_runner-0.0.4.dist-info/RECORD
