Metadata-Version: 2.3
Name: z-gitlab-runner
Version: 0.0.4
Project-URL: Documentation, https://github.com/MehdiChelh/z-gitlab-runner#readme
Project-URL: Issues, https://github.com/MehdiChelh/z-gitlab-runner/issues
Project-URL: Source, https://github.com/MehdiChelh/z-gitlab-runner
Author-email: MehdiChelh <mehdi.echel@gmail.com>
License-Expression: MIT
License-File: LICENSE.txt
Classifier: Development Status :: 4 - Beta
Classifier: Programming Language :: Python
Classifier: Programming Language :: Python :: 3.8
Classifier: Programming Language :: Python :: 3.9
Classifier: Programming Language :: Python :: 3.10
Classifier: Programming Language :: Python :: 3.11
Classifier: Programming Language :: Python :: 3.12
Classifier: Programming Language :: Python :: Implementation :: CPython
Classifier: Programming Language :: Python :: Implementation :: PyPy
Requires-Python: >=3.8
